.gitignore
.gitmodules
CHANGES.txt
LICENSE.txt
README.txt
bootstrap.py
buildout.cfg
pavement.py
setup.cfg
setup.py
doc/api.txt
doc/changes.txt
doc/client.txt
doc/conf.py
doc/development.txt
doc/index.txt
doc/installing.txt
doc/license.txt
doc/server.txt
doc/_static/_empty
doc/build/html
xdserver/__init__.py
xdserver/client.py
xdserver/server.py
xdserver.egg-info/PKG-INFO
xdserver.egg-info/SOURCES.txt
xdserver.egg-info/dependency_links.txt
xdserver.egg-info/entry_points.txt
xdserver.egg-info/not-zip-safe
xdserver.egg-info/requires.txt
xdserver.egg-info/top_level.txt