Metadata-Version: 1.0
Name: xdserver
Version: 3.9.1
Summary: Extended Durus Server
Home-page: http://11craft.github.com/xdserver/
Author: ElevenCraft Inc.
Author-email: matt@11craft.com
License: MIT
Platform: UNKNOWN
